CHANGES.rst
LICENSE.rst
MANIFEST.in
README.rst
setup.cfg
setup.py
tox.ini
docs/Makefile
docs/api.rst
docs/changelog.rst
docs/conf.py
docs/config.rst
docs/index.rst
docs/license.rst
docs/patterns.rst
docs/quickstart.rst
docs/_static/flask-coney-logo.png
docs/_static/flask-coney-title.png
examples/hello_world/README.rst
examples/hello_world/docker-compose.yaml
examples/hello_world/service1/Dockerfile
examples/hello_world/service1/app.py
examples/hello_world/service1/requirements.in
examples/hello_world/service1/requirements.txt
examples/hello_world/service2/Dockerfile
examples/hello_world/service2/app.py
examples/hello_world/service2/requirements.in
examples/hello_world/service2/requirements.txt
src/Flask_Coney.egg-info/PKG-INFO
src/Flask_Coney.egg-info/SOURCES.txt
src/Flask_Coney.egg-info/dependency_links.txt
src/Flask_Coney.egg-info/requires.txt
src/Flask_Coney.egg-info/top_level.txt
src/flask_coney/__init__.py
src/flask_coney/encoder.py
tests/__init__.py
tests/conftest.py
tests/test_coney.py
tests/test_encoder.py