Metadata-Version: 2.1
Name: Flask-Coney
Version: 1.1.3
Summary: Add Pika support to your Flask application.
Home-page: https://github.com/mikebarkmin/flask-coney
Author: Mike Barkmin
Author-email: mike@barkmin.eu
Maintainer: Mike Barkmin
Maintainer-email: mike@barkmin.eu
License: MIT
Project-URL: Documentation, https://mikebarkmin.github.io/flask-coney
Project-URL: Code, https://github.com/mikebarkmin/flask-coney
Project-URL: Issue tracker, https://github.com/mikebarkmin/flask-coney/issues
Platform: UNKNOWN
Classifier: Development Status :: 5 - Production/Stable
Classifier: Environment :: Web Environment
Classifier: Intended Audience :: Developers
Classifier: License :: OSI Approved :: MIT License
Classifier: Operating System :: OS Independent
Classifier: Programming Language :: Python
Classifier: Topic :: Internet :: WWW/HTTP :: Dynamic Content
Requires-Python: >=3.6
